{
    "LTP1": 0.05,
    "LTD1": -6.0,
    "Init_PFPC": 4.0,

    "LTP2": 1e-5,
    "LTD2": -1e-6,
    "Init_MFDCN": 0.07,
    "Init_MFDCN_low": 0.06,
    "Init_MFDCN_high": 0.11,

    "LTP3": 1e-7,
    "LTD3": 1e-6,
    "Init_PCDCN": -20.0,

    "PLAST1": true,
    "PLAST2": false,
    "PLAST3": false,

    "GR_num": 2000,
    "PC_num": 100,

    "test_types": [1, 2, 3],

    "train_time": 3000.00,
    "test_time": 6000.00,
    "t_stimulus_start": 0.00,
    "t_stimulus_end": 1000.00,
    "t_stimulus_duration": 1000.00
}